cube_dbt-0.6.3.dist-info/METADATA
cube_dbt-0.6.3.dist-info/WHEEL
cube_dbt-0.6.3.dist-info/entry_points.txt
cube_dbt/__init__.py
cube_dbt/column.py
cube_dbt/dbt.py
cube_dbt/dump.py
cube_dbt/model.py
cube_dbt-0.6.3.dist-info/RECORD
