Metadata-Version: 2.1
Name: cube_dbt
Version: 0.6.3
Summary: dbt integration for Cube
Author-Email: Artyom Keydunov <artyom@cube.dev>, Igor Lukanin <igor@cube.dev>, Paco Valdez <paco@cube.dev>
License: MIT
Requires-Python: >=3.8
Requires-Dist: PyYAML>=6.0.1
Requires-Dist: orjson>=3.10.15
